janet/__init__.py
janet/__main__.py
janet/api/__init__.py
janet/api/autocompleter.py
janet/api/check_for_imports.py
janet/api/cli_utils.py
janet/api/janet_record.py
janet/api/pip_index.py
janet/api/run.py
janet-0.2.1.dist-info/LICENSE
janet-0.2.1.dist-info/METADATA
janet-0.2.1.dist-info/WHEEL
janet-0.2.1.dist-info/top_level.txt
janet-0.2.1.dist-info/RECORD
