Metadata-Version: 2.1
Name: janet
Version: 0.2.1
Summary: Janet: manage your python projects more efficiently
Home-page: https://github.com/veryprofessionalusername/janet
Author: Amr Ahmed
Author-email: amrahmed.business@gmail.com
License: UNKNOWN
Platform: UNKNOWN
Classifier: Programming Language :: Python :: 3
Classifier: License :: OSI Approved :: GNU General Public License (GPL)
Classifier: Operating System :: OS Independent
Requires-Python: >=3.6
License-File: LICENSE
Requires-Dist: colorama
Requires-Dist: apscheduler
Requires-Dist: pyfiglet
Requires-Dist: bs4
